umm/C.py
umm/__init__.py
umm/__main__.py
umm/main.py
umm/mirrors.yml
umm/utils.py
umm/commands/__init__.py
umm/commands/base.py
umm/commands/brew.py
umm/commands/composer.py
umm/commands/golang.py
umm/commands/npm.py
umm/commands/pip.py
umm-0.6.1.dist-info/LICENSE
umm-0.6.1.dist-info/METADATA
umm-0.6.1.dist-info/WHEEL
umm-0.6.1.dist-info/entry_points.txt
umm-0.6.1.dist-info/top_level.txt
umm-0.6.1.dist-info/RECORD
