Metadata-Version: 2.1
Name: umm
Version: 0.6.1
Summary: A toolkit to manager the fastest mirror of various tools, such as pip, npm, composer and etc.
Home-page: https://github.com/xiyusullos/umm
Author: aponder
Author-email: i@aponder.top
License: MIT
Platform: UNKNOWN
Classifier: License :: OSI Approved :: MIT License
Classifier: Programming Language :: Python
Classifier: Programming Language :: Python :: 3.6
Classifier: Programming Language :: Python :: Implementation :: CPython
Classifier: Programming Language :: Python :: Implementation :: PyPy
Requires-Python: >=3.6.0
License-File: LICENSE
Requires-Dist: click
Requires-Dist: PyYAML
